[
    {
        "pubDate": "2025-3-28",
        "execution_timestamp": "2025-05-01 17;42;04",
        "organization": "RoAD to the L4",
        "title": "「資料・リンク」",
        "link": "https://www.road-to-the-l4.go.jp/publication/#anc01",
        "summary": ""
    },
    {
        "pubDate": "2025-3-6",
        "execution_timestamp": "2025-05-01 17;42;04",
        "organization": "RoAD to the L4",
        "title": "「Road to the L4事業」ウェブサイトの英語ページを公開しました。",
        "link": "https://www.road-to-the-l4.go.jp/en/",
        "summary": ""
    },
    {
        "pubDate": "2025-3-6",
        "execution_timestamp": "2025-05-01 17;42;04",
        "organization": "RoAD to the L4",
        "title": "こちら",
        "link": "https://www.road-to-the-l4.go.jp/activity/guideline/",
        "summary": ""
    },
    {
        "pubDate": "2023-07-31",
        "execution_timestamp": "2025-05-01 17;42;04",
        "organization": "RoAD to the L4",
        "title": "資料・リンク",
        "link": "https://www.road-to-the-l4.go.jp/publication/",
        "summary": ""
    }
]